gradient_ascent/__init__.py
gradient_ascent/main.py
gradient_ascent-0.0.2.dist-info/LICENSE
gradient_ascent-0.0.2.dist-info/WHEEL
gradient_ascent-0.0.2.dist-info/METADATA
gradient_ascent-0.0.2.dist-info/RECORD
